{
  "date": "02-03-2026",
  "title": "Xổ số Miền Nam Thứ Hai 02-03-2026",
  "regions": [
    "Hồ Chí Minh",
    "Đồng Tháp",
    "Cà Mau"
  ],
  "prizes": {
    "Giải tám": {
      "Hồ Chí Minh": [
        "38"
      ],
      "Đồng Tháp": [
        "49"
      ],
      "Cà Mau": [
        "47"
      ]
    },
    "Giải bảy": {
      "Hồ Chí Minh": [
        "945"
      ],
      "Đồng Tháp": [
        "093"
      ],
      "Cà Mau": [
        "083"
      ]
    },
    "Giải sáu": {
      "Hồ Chí Minh": [
        "2937",
        "4514",
        "3104"
      ],
      "Đồng Tháp": [
        "7717",
        "6469",
        "5452"
      ],
      "Cà Mau": [
        "3628",
        "5869",
        "8037"
      ]
    },
    "Giải năm": {
      "Hồ Chí Minh": [
        "6087"
      ],
      "Đồng Tháp": [
        "9287"
      ],
      "Cà Mau": [
        "7334"
      ]
    },
    "Giải tư": {
      "Hồ Chí Minh": [
        "46630",
        "14507",
        "70658",
        "50445",
        "11299",
        "41446",
        "40070"
      ],
      "Đồng Tháp": [
        "60175",
        "06025",
        "41522",
        "20667",
        "29807",
        "43199",
        "48178"
      ],
      "Cà Mau": [
        "61439",
        "46471",
        "04875",
        "54820",
        "39974",
        "06322",
        "69809"
      ]
    },
    "Giải ba": {
      "Hồ Chí Minh": [
        "29388",
        "80957"
      ],
      "Đồng Tháp": [
        "44725",
        "68290"
      ],
      "Cà Mau": [
        "33633",
        "61189"
      ]
    },
    "Giải nhì": {
      "Hồ Chí Minh": [
        "81681"
      ],
      "Đồng Tháp": [
        "87662"
      ],
      "Cà Mau": [
        "77597"
      ]
    },
    "Giải nhất": {
      "Hồ Chí Minh": [
        "74571"
      ],
      "Đồng Tháp": [
        "14852"
      ],
      "Cà Mau": [
        "28927"
      ]
    },
    "Đặc biệt": {
      "Hồ Chí Minh": [
        "733819"
      ],
      "Đồng Tháp": [
        "712198"
      ],
      "Cà Mau": [
        "253447"
      ]
    }
  }
}