{
  "date": "09-12-2025",
  "title": "Xổ số Miền Nam Thứ Ba 09-12-2025",
  "regions": [
    "Bến Tre",
    "Vũng Tàu",
    "Bạc Liêu"
  ],
  "prizes": {
    "Giải tám": {
      "Bến Tre": [
        "14"
      ],
      "Vũng Tàu": [
        "98"
      ],
      "Bạc Liêu": [
        "55"
      ]
    },
    "Giải bảy": {
      "Bến Tre": [
        "454"
      ],
      "Vũng Tàu": [
        "536"
      ],
      "Bạc Liêu": [
        "183"
      ]
    },
    "Giải sáu": {
      "Bến Tre": [
        "3533",
        "6053",
        "2022"
      ],
      "Vũng Tàu": [
        "1251",
        "9590",
        "7325"
      ],
      "Bạc Liêu": [
        "7334",
        "6560",
        "5367"
      ]
    },
    "Giải năm": {
      "Bến Tre": [
        "4661"
      ],
      "Vũng Tàu": [
        "6328"
      ],
      "Bạc Liêu": [
        "0162"
      ]
    },
    "Giải tư": {
      "Bến Tre": [
        "57046",
        "48629",
        "66624",
        "67954",
        "26387",
        "38907",
        "80913"
      ],
      "Vũng Tàu": [
        "15700",
        "28847",
        "70990",
        "74252",
        "74351",
        "84161",
        "85030"
      ],
      "Bạc Liêu": [
        "81357",
        "30701",
        "32670",
        "66991",
        "53993",
        "35197",
        "31514"
      ]
    },
    "Giải ba": {
      "Bến Tre": [
        "41090",
        "88956"
      ],
      "Vũng Tàu": [
        "70513",
        "96313"
      ],
      "Bạc Liêu": [
        "36163",
        "32723"
      ]
    },
    "Giải nhì": {
      "Bến Tre": [
        "19021"
      ],
      "Vũng Tàu": [
        "18343"
      ],
      "Bạc Liêu": [
        "50302"
      ]
    },
    "Giải nhất": {
      "Bến Tre": [
        "66629"
      ],
      "Vũng Tàu": [
        "21445"
      ],
      "Bạc Liêu": [
        "02302"
      ]
    },
    "Đặc biệt": {
      "Bến Tre": [
        "257886"
      ],
      "Vũng Tàu": [
        "000248"
      ],
      "Bạc Liêu": [
        "086267"
      ]
    }
  }
}