{
  "date": "27-06-2026",
  "title": "Xổ số Miền Nam Thứ Bảy 27-06-2026",
  "regions": [
    "Hồ Chí Minh",
    "Long An",
    "Bình Phước",
    "Hậu Giang"
  ],
  "prizes": {
    "Giải tám": {
      "Hồ Chí Minh": [
        "28"
      ],
      "Long An": [
        "17"
      ],
      "Bình Phước": [
        "70"
      ],
      "Hậu Giang": [
        "76"
      ]
    },
    "Giải bảy": {
      "Hồ Chí Minh": [
        "347"
      ],
      "Long An": [
        "849"
      ],
      "Bình Phước": [
        "488"
      ],
      "Hậu Giang": [
        "988"
      ]
    },
    "Giải sáu": {
      "Hồ Chí Minh": [
        "9653",
        "1646",
        "3249"
      ],
      "Long An": [
        "0424",
        "4408",
        "2122"
      ],
      "Bình Phước": [
        "7084",
        "9522",
        "4266"
      ],
      "Hậu Giang": [
        "9266",
        "5701",
        "3559"
      ]
    },
    "Giải năm": {
      "Hồ Chí Minh": [
        "6693"
      ],
      "Long An": [
        "9878"
      ],
      "Bình Phước": [
        "0518"
      ],
      "Hậu Giang": [
        "6058"
      ]
    },
    "Giải tư": {
      "Hồ Chí Minh": [
        "97524",
        "01564",
        "08337",
        "40767",
        "21162",
        "59787",
        "85176"
      ],
      "Long An": [
        "80612",
        "87582",
        "27718",
        "89687",
        "23436",
        "63802",
        "53319"
      ],
      "Bình Phước": [
        "51208",
        "30040",
        "37569",
        "89543",
        "31483",
        "42386",
        "17119"
      ],
      "Hậu Giang": [
        "84763",
        "88658",
        "50953",
        "80665",
        "67969",
        "95068",
        "07193"
      ]
    },
    "Giải ba": {
      "Hồ Chí Minh": [
        "21088",
        "20190"
      ],
      "Long An": [
        "92338",
        "67326"
      ],
      "Bình Phước": [
        "57100",
        "34668"
      ],
      "Hậu Giang": [
        "86269",
        "33280"
      ]
    },
    "Giải nhì": {
      "Hồ Chí Minh": [
        "82478"
      ],
      "Long An": [
        "78517"
      ],
      "Bình Phước": [
        "37665"
      ],
      "Hậu Giang": [
        "85191"
      ]
    },
    "Giải nhất": {
      "Hồ Chí Minh": [
        "06554"
      ],
      "Long An": [
        "49583"
      ],
      "Bình Phước": [
        "37597"
      ],
      "Hậu Giang": [
        "15307"
      ]
    },
    "Đặc biệt": {
      "Hồ Chí Minh": [
        "608165"
      ],
      "Long An": [
        "218731"
      ],
      "Bình Phước": [
        "311230"
      ],
      "Hậu Giang": [
        "778736"
      ]
    }
  }
}