{
  "date": "14-04-2026",
  "title": "Xổ số Miền Nam Thứ Ba 14-04-2026",
  "regions": [
    "Bến Tre",
    "Vũng Tàu",
    "Bạc Liêu"
  ],
  "prizes": {
    "Giải tám": {
      "Bến Tre": [
        "10"
      ],
      "Vũng Tàu": [
        "31"
      ],
      "Bạc Liêu": [
        "45"
      ]
    },
    "Giải bảy": {
      "Bến Tre": [
        "094"
      ],
      "Vũng Tàu": [
        "324"
      ],
      "Bạc Liêu": [
        "937"
      ]
    },
    "Giải sáu": {
      "Bến Tre": [
        "4068",
        "4575",
        "1155"
      ],
      "Vũng Tàu": [
        "3858",
        "2210",
        "0654"
      ],
      "Bạc Liêu": [
        "1938",
        "1950",
        "8160"
      ]
    },
    "Giải năm": {
      "Bến Tre": [
        "8216"
      ],
      "Vũng Tàu": [
        "8073"
      ],
      "Bạc Liêu": [
        "0029"
      ]
    },
    "Giải tư": {
      "Bến Tre": [
        "81455",
        "85385",
        "94879",
        "15258",
        "56808",
        "69975",
        "20511"
      ],
      "Vũng Tàu": [
        "71762",
        "42222",
        "80690",
        "05728",
        "69430",
        "60759",
        "29930"
      ],
      "Bạc Liêu": [
        "20865",
        "72398",
        "11814",
        "82545",
        "45675",
        "83131",
        "48893"
      ]
    },
    "Giải ba": {
      "Bến Tre": [
        "65850",
        "66305"
      ],
      "Vũng Tàu": [
        "64120",
        "61574"
      ],
      "Bạc Liêu": [
        "30808",
        "97499"
      ]
    },
    "Giải nhì": {
      "Bến Tre": [
        "25790"
      ],
      "Vũng Tàu": [
        "58385"
      ],
      "Bạc Liêu": [
        "79068"
      ]
    },
    "Giải nhất": {
      "Bến Tre": [
        "50733"
      ],
      "Vũng Tàu": [
        "24529"
      ],
      "Bạc Liêu": [
        "82272"
      ]
    },
    "Đặc biệt": {
      "Bến Tre": [
        "966588"
      ],
      "Vũng Tàu": [
        "433594"
      ],
      "Bạc Liêu": [
        "499850"
      ]
    }
  }
}