{
  "date": "03-07-2025",
  "title": "Xổ số Miền Nam Thứ năm 03-07-2025",
  "regions": [
    "Tây Ninh",
    "An Giang",
    "Bình Thuận"
  ],
  "prizes": {
    "Giải tám": {
      "Tây Ninh": [
        "32"
      ],
      "An Giang": [
        "62"
      ],
      "Bình Thuận": [
        "79"
      ]
    },
    "Giải bảy": {
      "Tây Ninh": [
        "663"
      ],
      "An Giang": [
        "240"
      ],
      "Bình Thuận": [
        "026"
      ]
    },
    "Giải sáu": {
      "Tây Ninh": [
        "9643",
        "5374",
        "3977"
      ],
      "An Giang": [
        "3917",
        "5372",
        "0368"
      ],
      "Bình Thuận": [
        "9752",
        "3977",
        "7893"
      ]
    },
    "Giải năm": {
      "Tây Ninh": [
        "7060"
      ],
      "An Giang": [
        "5658"
      ],
      "Bình Thuận": [
        "3371"
      ]
    },
    "Giải tư": {
      "Tây Ninh": [
        "06282",
        "77820",
        "59132",
        "86470",
        "27611",
        "90508",
        "68147"
      ],
      "An Giang": [
        "81878",
        "28395",
        "15365",
        "23708",
        "21794",
        "09033",
        "38195"
      ],
      "Bình Thuận": [
        "41468",
        "98089",
        "56257",
        "10743",
        "70968",
        "98873",
        "07316"
      ]
    },
    "Giải ba": {
      "Tây Ninh": [
        "22993",
        "83443"
      ],
      "An Giang": [
        "02623",
        "67330"
      ],
      "Bình Thuận": [
        "23842",
        "64780"
      ]
    },
    "Giải nhì": {
      "Tây Ninh": [
        "69693"
      ],
      "An Giang": [
        "37116"
      ],
      "Bình Thuận": [
        "30930"
      ]
    },
    "Giải nhất": {
      "Tây Ninh": [
        "60888"
      ],
      "An Giang": [
        "23919"
      ],
      "Bình Thuận": [
        "80914"
      ]
    },
    "Đặc biệt": {
      "Tây Ninh": [
        "804174"
      ],
      "An Giang": [
        "059381"
      ],
      "Bình Thuận": [
        "157627"
      ]
    }
  }
}