{
  "date": "12-04-2025",
  "title": "Xổ số Miền Nam Thứ Bảy 12-04-2025",
  "regions": [
    "Hồ Chí Minh",
    "Long An",
    "Bình Phước",
    "Hậu Giang"
  ],
  "prizes": {
    "Giải tám": {
      "Hồ Chí Minh": "44",
      "Long An": "92",
      "Bình Phước": "18",
      "Hậu Giang": "82"
    },
    "Giải bảy": {
      "Hồ Chí Minh": "079",
      "Long An": "731",
      "Bình Phước": "611",
      "Hậu Giang": "432"
    },
    "Giải sáu": {
      "Hồ Chí Minh": "0270",
      "Long An": "8025",
      "Bình Phước": "5928",
      "Hậu Giang": "1314"
    },
    "Giải năm": {
      "Hồ Chí Minh": "8956",
      "Long An": "8534",
      "Bình Phước": "4063",
      "Hậu Giang": "9208"
    },
    "Giải tư": {
      "Hồ Chí Minh": "42164",
      "Long An": "73761",
      "Bình Phước": "97122",
      "Hậu Giang": "63725"
    },
    "Giải ba": {
      "Hồ Chí Minh": "57854",
      "Long An": "60365",
      "Bình Phước": "59498",
      "Hậu Giang": "70451"
    },
    "Giải nhì": {
      "Hồ Chí Minh": "07448",
      "Long An": "73633",
      "Bình Phước": "74869",
      "Hậu Giang": "80307"
    },
    "Giải nhất": {
      "Hồ Chí Minh": "88379",
      "Long An": "48454",
      "Bình Phước": "87785",
      "Hậu Giang": "34080"
    },
    "Đặc biệt": {
      "Hồ Chí Minh": "259054",
      "Long An": "714844",
      "Bình Phước": "339612",
      "Hậu Giang": "959814"
    }
  }
}