{
  "date": "24-08-2025",
  "title": "Xổ số Miền Nam Chủ Nhật 24-08-2025",
  "regions": [
    "Tiền Giang",
    "Kiên Giang",
    "Đà Lạt"
  ],
  "prizes": {
    "Giải tám": {
      "Tiền Giang": [
        "10"
      ],
      "Kiên Giang": [
        "55"
      ],
      "Đà Lạt": [
        "02"
      ]
    },
    "Giải bảy": {
      "Tiền Giang": [
        "315"
      ],
      "Kiên Giang": [
        "308"
      ],
      "Đà Lạt": [
        "860"
      ]
    },
    "Giải sáu": {
      "Tiền Giang": [
        "3923",
        "7918",
        "4085"
      ],
      "Kiên Giang": [
        "8816",
        "0882",
        "0841"
      ],
      "Đà Lạt": [
        "1234",
        "9684",
        "1488"
      ]
    },
    "Giải năm": {
      "Tiền Giang": [
        "5285"
      ],
      "Kiên Giang": [
        "1941"
      ],
      "Đà Lạt": [
        "5492"
      ]
    },
    "Giải tư": {
      "Tiền Giang": [
        "43060",
        "81130",
        "38287",
        "24505",
        "47277",
        "65471",
        "62602"
      ],
      "Kiên Giang": [
        "04527",
        "89980",
        "79682",
        "41281",
        "82663",
        "84773",
        "09324"
      ],
      "Đà Lạt": [
        "10548",
        "22217",
        "19796",
        "31572",
        "76016",
        "57758",
        "98895"
      ]
    },
    "Giải ba": {
      "Tiền Giang": [
        "62537",
        "87705"
      ],
      "Kiên Giang": [
        "91919",
        "14069"
      ],
      "Đà Lạt": [
        "19171",
        "10365"
      ]
    },
    "Giải nhì": {
      "Tiền Giang": [
        "22764"
      ],
      "Kiên Giang": [
        "36601"
      ],
      "Đà Lạt": [
        "11002"
      ]
    },
    "Giải nhất": {
      "Tiền Giang": [
        "88995"
      ],
      "Kiên Giang": [
        "16551"
      ],
      "Đà Lạt": [
        "65348"
      ]
    },
    "Đặc biệt": {
      "Tiền Giang": [
        "451272"
      ],
      "Kiên Giang": [
        "457411"
      ],
      "Đà Lạt": [
        "380438"
      ]
    }
  }
}